gestion_banco_vega_salgado/__init__.py
gestion_banco_vega_salgado/cajero.py
gestion_banco_vega_salgado/cliente.py
gestion_banco_vega_salgado/cuenta.py
gestion_banco_vega_salgado/transaccion.py
gestion_banco_vega_salgado-1.0.0.dist-info/licenses/LICENSE
gestion_banco_vega_salgado-1.0.0.dist-info/METADATA
gestion_banco_vega_salgado-1.0.0.dist-info/WHEEL
gestion_banco_vega_salgado-1.0.0.dist-info/top_level.txt
gestion_banco_vega_salgado-1.0.0.dist-info/RECORD
