Metadata-Version: 2.4
Name: gestion_banco_vega_salgado
Version: 1.0.0
Summary: Sistema bancario con POO en Python
Home-page: https://github.com/usuario/gestion_banco_vega_salgado
Author: Alfonso Fernando Vega Salgado
Author-email: poleoperris12359@gmail.com
Requires-Python: >=3.6
License-File: LICENSE
Dynamic: author
Dynamic: author-email
Dynamic: description
Dynamic: description-content-type
Dynamic: home-page
Dynamic: license-file
Dynamic: requires-python
Dynamic: summary
